tomopt/__init__.py
tomopt/benchmarks/__init__.py
tomopt/benchmarks/ladle_furnace/__init__.py
tomopt/benchmarks/ladle_furnace/data.py
tomopt/benchmarks/ladle_furnace/inference.py
tomopt/benchmarks/ladle_furnace/loss.py
tomopt/benchmarks/ladle_furnace/plotting.py
tomopt/benchmarks/ladle_furnace/volume.py
tomopt/benchmarks/small_walls/__init__.py
tomopt/benchmarks/small_walls/data.py
tomopt/benchmarks/small_walls/volume.py
tomopt/benchmarks/u_lorry/__init__.py
tomopt/benchmarks/u_lorry/data.py
tomopt/core.py
tomopt/inference/__init__.py
tomopt/inference/scattering.py
tomopt/inference/volume.py
tomopt/muon/__init__.py
tomopt/muon/generation.py
tomopt/muon/muon_batch.py
tomopt/optimisation/__init__.py
tomopt/optimisation/callbacks/__init__.py
tomopt/optimisation/callbacks/callback.py
tomopt/optimisation/callbacks/cyclic_callbacks.py
tomopt/optimisation/callbacks/data_callbacks.py
tomopt/optimisation/callbacks/detector_callbacks.py
tomopt/optimisation/callbacks/diagnostic_callbacks.py
tomopt/optimisation/callbacks/eval_metric.py
tomopt/optimisation/callbacks/grad_callbacks.py
tomopt/optimisation/callbacks/heatmap_gif.py
tomopt/optimisation/callbacks/monitors.py
tomopt/optimisation/callbacks/opt_callbacks.py
tomopt/optimisation/callbacks/pred_callbacks.py
tomopt/optimisation/callbacks/warmup_callbacks.py
tomopt/optimisation/data/__init__.py
tomopt/optimisation/data/passives.py
tomopt/optimisation/loss/__init__.py
tomopt/optimisation/loss/loss.py
tomopt/optimisation/loss/sub_losses.py
tomopt/optimisation/wrapper/__init__.py
tomopt/optimisation/wrapper/volume_wrapper.py
tomopt/plotting/__init__.py
tomopt/plotting/appearance.py
tomopt/plotting/diagnostics.py
tomopt/plotting/predictions.py
tomopt/py.typed
tomopt/utils.py
tomopt/version.py
tomopt/volume/__init__.py
tomopt/volume/heatmap.py
tomopt/volume/layer.py
tomopt/volume/panel.py
tomopt/volume/scatter_model.py
tomopt/volume/scatter_models/dt_dx_10mm.hdf5
tomopt/volume/volume.py
tomopt-0.1.0.dist-info/LICENSE
tomopt-0.1.0.dist-info/METADATA
tomopt-0.1.0.dist-info/WHEEL
tomopt-0.1.0.dist-info/RECORD
