Metadata-Version: 2.1
Name: tomopt
Version: 0.1.0
Summary: TomOpt: Differential Muon Tomography Optimisation.
Home-page: https://mode-collaboration.github.io/
License: AGPL-3.0-only
Keywords: deep learning,differential programming,physics,science,statistics,tomography,detector
Author: Giles Strong
Author-email: giles.c.strong@gmail.com
Requires-Python: >=3.10,<4.0
Classifier: Development Status :: 3 - Alpha
Classifier: Intended Audience :: Developers
Classifier: Intended Audience :: Science/Research
Classifier: License :: OSI Approved :: GNU Affero General Public License v3
Classifier: Natural Language :: English
Classifier: Programming Language :: Python :: 3
Classifier: Programming Language :: Python :: 3.10
Classifier: Programming Language :: Python :: 3.11
Classifier: Programming Language :: Python :: 3.12
Requires-Dist: fastcore (==1.3.20)
Requires-Dist: fastprogress (==1.0.0)
Requires-Dist: h5py (>=3.10.0,<4.0.0)
Requires-Dist: imageio (==2.16.2)
Requires-Dist: matplotlib (>=3.7.0,<3.8.0)
Requires-Dist: numpy (>=1.26.4,<2.0.0)
Requires-Dist: pandas (>=1.2.4,<2.0.0)
Requires-Dist: particle (>=0.23.1,<0.24.0)
Requires-Dist: prettytable (>=3.9.0,<4.0.0)
Requires-Dist: seaborn (>=0.11.0,<0.12.0)
Requires-Dist: torch (>=2.2.0,<3.0.0)
Project-URL: Documentation, https://tomopt.readthedocs.io/en/stable
